sekoia_automation/__init__.py
sekoia_automation/account_validator.py
sekoia_automation/action.py
sekoia_automation/aio/__init__.py
sekoia_automation/aio/connector.py
sekoia_automation/aio/helpers/__init__.py
sekoia_automation/aio/helpers/aws/__init__.py
sekoia_automation/aio/helpers/aws/client.py
sekoia_automation/aio/helpers/files/__init__.py
sekoia_automation/aio/helpers/files/csv.py
sekoia_automation/aio/helpers/files/utils.py
sekoia_automation/aio/helpers/http/__init__.py
sekoia_automation/aio/helpers/http/utils.py
sekoia_automation/asset_connector/__init__.py
sekoia_automation/asset_connector/models/__init__.py
sekoia_automation/asset_connector/models/connector.py
sekoia_automation/asset_connector/models/ocsf/__init__.py
sekoia_automation/asset_connector/models/ocsf/base.py
sekoia_automation/asset_connector/models/ocsf/device.py
sekoia_automation/asset_connector/models/ocsf/group.py
sekoia_automation/asset_connector/models/ocsf/organization.py
sekoia_automation/asset_connector/models/ocsf/risk_level.py
sekoia_automation/asset_connector/models/ocsf/software.py
sekoia_automation/asset_connector/models/ocsf/user.py
sekoia_automation/asset_connector/models/ocsf/vulnerability.py
sekoia_automation/checkpoint.py
sekoia_automation/cli.py
sekoia_automation/config.py
sekoia_automation/configuration/__init__.py
sekoia_automation/configuration/base.py
sekoia_automation/configuration/filesystem.py
sekoia_automation/configuration/fission.py
sekoia_automation/configuration/utils.py
sekoia_automation/connector/__init__.py
sekoia_automation/connector/metrics.py
sekoia_automation/connector/workers.py
sekoia_automation/constants.py
sekoia_automation/exceptions.py
sekoia_automation/http/__init__.py
sekoia_automation/http/aio/__init__.py
sekoia_automation/http/aio/http_client.py
sekoia_automation/http/aio/token_refresher.py
sekoia_automation/http/http_client.py
sekoia_automation/http/rate_limiter.py
sekoia_automation/http/retry.py
sekoia_automation/http/sync/__init__.py
sekoia_automation_sdk-1.22.1.dist-info/METADATA
sekoia_automation_sdk-1.22.1.dist-info/WHEEL
sekoia_automation_sdk-1.22.1.dist-info/entry_points.txt
sekoia_automation_sdk-1.22.1.dist-info/licenses/LICENSE
sekoia_automation_sdk-1.22.1.dist-info/RECORD
