Metadata-Version: 2.4
Name: sekoia-automation-sdk
Version: 1.22.1
Summary: SDK to create Sekoia.io playbook modules
License: MIT
License-File: LICENSE
Keywords: SDK,Sekoia.io,automation,playbook
Author: Sekoia.io
Requires-Python: >=3.11,<4.0
Classifier: Intended Audience :: Developers
Classifier: License :: OSI Approved :: MIT License
Classifier: Natural Language :: English
Classifier: Programming Language :: Python :: 3
Classifier: Programming Language :: Python :: 3.11
Classifier: Programming Language :: Python :: 3.12
Classifier: Programming Language :: Python :: 3.13
Classifier: Programming Language :: Python :: 3.14
Classifier: Topic :: Security
Classifier: Topic :: Software Development :: Libraries
Provides-Extra: all
Provides-Extra: async-aws
Provides-Extra: async-files
Provides-Extra: async-http
Provides-Extra: logging
Requires-Dist: Jinja2 (>=3.0.3,<4.0.0)
Requires-Dist: PyYAML (>=6.0,<7.0)
Requires-Dist: aiobotocore (>=2.20.0,<3.0.0) ; extra == "all" or extra == "async-aws"
Requires-Dist: aiocsv (>=1.2.4,<2.0.0) ; extra == "all" or extra == "async-files"
Requires-Dist: aiofiles (>=23.1.0,<24.0.0) ; extra == "all" or extra == "async-http" or extra == "async-files"
Requires-Dist: aiohttp (>=3.8.4,<4.0.0)
Requires-Dist: aiolimiter (>=1.1.0,<2.0.0) ; extra == "all" or extra == "async-http"
Requires-Dist: black
Requires-Dist: boto3 (>=1.36.23,<2.0.0) ; extra == "all" or extra == "async-aws"
Requires-Dist: cachetools (>=6.2.3,<7.0.0)
Requires-Dist: cookiecutter (>=2.1,<3.0)
Requires-Dist: flask (>=3.1.2,<4.0.0)
Requires-Dist: jsonschema (>=4.22.0,<5.0.0)
Requires-Dist: loguru (>=0.7.0,<0.8.0) ; extra == "all" or extra == "logging"
Requires-Dist: orjson (>=3.8,<4.0)
Requires-Dist: poetry
Requires-Dist: prometheus-client (>=0.21.0,<0.22.0)
Requires-Dist: pydantic (>=2.10,<3.0)
Requires-Dist: python-slugify (>=5.0.2,<6.0.0)
Requires-Dist: requests (>=2.25,<3.0)
Requires-Dist: requests-ratelimiter (>=0.7.0,<0.8.0)
Requires-Dist: s3path (>=0.6.4,<0.7.0)
Requires-Dist: sentry-sdk
Requires-Dist: tenacity
Requires-Dist: typer[all] (>=0.17.3,<0.18.0)
Project-URL: Documentation, https://docs.sekoia.io/
Project-URL: Homepage, https://sekoia.io/
Project-URL: Repository, https://github.com/SEKOIA-IO/sekoia-automation-sdk
